[
  {
    "level": 1,
    "term": "\\(C\\left( {E,p,B}\\right)\\)",
    "sort_key": "C",
    "page": [
      487
    ]
  },
  {
    "level": 1,
    "term": "Classification: of covering spaces",
    "page": [
      482
    ]
  },
  {
    "level": 2,
    "term": "of covering transformations",
    "page": [
      488
    ],
    "parent": "Classification: of covering spaces"
  },
  {
    "level": 2,
    "term": "of covering maps",
    "page": [
      341,
      485,
      487
    ],
    "parent": "Composite: of functions"
  },
  {
    "level": 1,
    "term": "Cone",
    "page": [
      499
    ]
  },
  {
    "level": 1,
    "term": "Conjugacy class",
    "page": [
      481
    ]
  },
  {
    "level": 1,
    "term": "Conjugate subgroups",
    "page": [
      481
    ]
  },
  {
    "level": 2,
    "term": "composite",
    "page": [
      341,
      485,
      487
    ],
    "parent": "Covering map"
  },
  {
    "level": 2,
    "term": "restrictions",
    "page": [
      338,
      484
    ],
    "parent": "Covering map"
  },
  {
    "level": 2,
    "term": "classification",
    "page": [
      482
    ],
    "parent": "Covering space"
  },
  {
    "level": 2,
    "term": "equivalence",
    "page": [
      478
    ],
    "parent": "Covering space"
  },
  {
    "level": 2,
    "term": "existence",
    "page": [
      495
    ],
    "parent": "Covering space"
  },
  {
    "level": 2,
    "term": "of figure eight",
    "page": [
      340,
      374,
      375,
      492,
      493
    ],
    "parent": "Covering space"
  },
  {
    "level": 2,
    "term": "regular",
    "page": [
      489
    ],
    "parent": "Covering space"
  },
  {
    "level": 2,
    "term": "of \\({S}^{1}\\)",
    "page": [
      337,
      338,
      482
    ],
    "parent": "Covering space"
  },
  {
    "level": 2,
    "term": "topological properties",
    "page": [
      341,
      500
    ],
    "parent": "Covering space"
  },
  {
    "level": 2,
    "term": "of torus",
    "page": [
      339,
      483
    ],
    "parent": "Covering space"
  },
  {
    "level": 2,
    "term": "universal",
    "page": [
      484
    ],
    "parent": "Covering space"
  },
  {
    "level": 1,
    "term": "Covering transformation",
    "page": [
      487
    ]
  },
  {
    "level": 1,
    "term": "Equivalence of covering maps",
    "page": [
      478
    ]
  },
  {
    "level": 2,
    "term": "existence",
    "page": [
      480,
      482
    ],
    "parent": "Equivalence of covering maps"
  },
  {
    "level": 2,
    "term": "covering space",
    "page": [
      340,
      374,
      375,
      492,
      493
    ],
    "parent": "Figure-eight space"
  },
  {
    "level": 1,
    "term": "Fixed-point-free action",
    "page": [
      493
    ]
  },
  {
    "level": 2,
    "term": "of infinite earring",
    "page": [
      500
    ],
    "parent": "Fundamental group"
  },
  {
    "level": 2,
    "term": "when countable",
    "page": [
      499,
      500
    ],
    "parent": "Fundamental group"
  },
  {
    "level": 2,
    "term": "when finitely generated",
    "page": [
      500
    ],
    "parent": "Fundamental group"
  },
  {
    "level": 2,
    "term": "when uncountable",
    "page": [
      500
    ],
    "parent": "Fundamental group"
  },
  {
    "level": 1,
    "term": "General lifting lemma",
    "page": [
      478
    ]
  },
  {
    "level": 1,
    "term": "Group of covering transformations",
    "page": [
      487
    ]
  },
  {
    "level": 2,
    "term": "fundamental group",
    "page": [
      500
    ],
    "parent": "Infinite earring"
  },
  {
    "level": 2,
    "term": "no universal covering",
    "page": [
      487
    ],
    "parent": "Infinite earring"
  },
  {
    "level": 1,
    "term": "Lens space",
    "page": [
      494
    ]
  },
  {
    "level": 1,
    "term": "Lifting lemma: general",
    "page": [
      478
    ]
  },
  {
    "level": 1,
    "term": "Local simple connectedness",
    "page": [
      495
    ]
  },
  {
    "level": 2,
    "term": "vs. simple connectedness",
    "page": [
      499
    ],
    "parent": "Local simple connectedness"
  },
  {
    "level": 1,
    "term": "Normalizer",
    "page": [
      487
    ]
  },
  {
    "level": 1,
    "term": "Orbit",
    "page": [
      490
    ]
  },
  {
    "level": 1,
    "term": "Orbit space",
    "page": [
      199,
      490
    ]
  },
  {
    "level": 1,
    "term": "Properly discontinuous",
    "page": [
      490
    ]
  },
  {
    "level": 1,
    "term": "Regular covering space",
    "page": [
      489
    ]
  },
  {
    "level": 2,
    "term": "is orbit space",
    "page": [
      491
    ],
    "parent": "Regular covering space"
  },
  {
    "level": 1,
    "term": "Restriction: of a covering map",
    "page": [
      338,
      484
    ]
  },
  {
    "level": 1,
    "term": "Semilocally simply connected",
    "page": [
      494
    ]
  },
  {
    "level": 2,
    "term": "vs. locally simply connected",
    "page": [
      499
    ],
    "parent": "Simply connected"
  },
  {
    "level": 2,
    "term": "covering spaces",
    "page": [
      337,
      482
    ],
    "parent": "\\({S}^{1}\\)"
  },
  {
    "level": 2,
    "term": "covering space of",
    "page": [
      483
    ],
    "parent": "Topological group"
  },
  {
    "level": 2,
    "term": "covering space of",
    "page": [
      339,
      483
    ],
    "parent": "Torus"
  },
  {
    "level": 1,
    "term": "Universal covering space",
    "page": [
      484
    ]
  },
  {
    "level": 2,
    "term": "existence",
    "page": [
      498
    ],
    "parent": "Universal covering space"
  }
]